rapids_singlecell/__init__.py
rapids_singlecell/_compat.py
rapids_singlecell/_version.py
rapids_singlecell/dcg.py
rapids_singlecell/gr.py
rapids_singlecell/pp.py
rapids_singlecell/tl.py
rapids_singlecell/_utils/__init__.py
rapids_singlecell/decoupler_gpu/__init__.py
rapids_singlecell/decoupler_gpu/_method_aucell.py
rapids_singlecell/decoupler_gpu/_method_mlm.py
rapids_singlecell/decoupler_gpu/_method_ulm.py
rapids_singlecell/decoupler_gpu/_method_waggr.py
rapids_singlecell/decoupler_gpu/_method_zscore.py
rapids_singlecell/decoupler_gpu/_helper/_Method.py
rapids_singlecell/decoupler_gpu/_helper/_data.py
rapids_singlecell/decoupler_gpu/_helper/_docs.py
rapids_singlecell/decoupler_gpu/_helper/_log.py
rapids_singlecell/decoupler_gpu/_helper/_net.py
rapids_singlecell/decoupler_gpu/_helper/_pv.py
rapids_singlecell/decoupler_gpu/_helper/_run.py
rapids_singlecell/get/__init__.py
rapids_singlecell/get/_aggregated.py
rapids_singlecell/get/_anndata.py
rapids_singlecell/get/_kernels/_aggr_kernels.py
rapids_singlecell/preprocessing/__init__.py
rapids_singlecell/preprocessing/_harmony_integrate.py
rapids_singlecell/preprocessing/_hvg.py
rapids_singlecell/preprocessing/_normalize.py
rapids_singlecell/preprocessing/_pca.py
rapids_singlecell/preprocessing/_qc.py
rapids_singlecell/preprocessing/_regress_out.py
rapids_singlecell/preprocessing/_scale.py
rapids_singlecell/preprocessing/_simple.py
rapids_singlecell/preprocessing/_utils.py
rapids_singlecell/preprocessing/_harmony/__init__.py
rapids_singlecell/preprocessing/_harmony/_fuses.py
rapids_singlecell/preprocessing/_harmony/_helper.py
rapids_singlecell/preprocessing/_harmony/_kernels/_kmeans.py
rapids_singlecell/preprocessing/_harmony/_kernels/_normalize.py
rapids_singlecell/preprocessing/_harmony/_kernels/_outer.py
rapids_singlecell/preprocessing/_harmony/_kernels/_pen.py
rapids_singlecell/preprocessing/_harmony/_kernels/_scatter_add.py
rapids_singlecell/preprocessing/_kernels/_mean_var_kernel.py
rapids_singlecell-0.13.5.dist-info/METADATA
rapids_singlecell-0.13.5.dist-info/WHEEL
rapids_singlecell-0.13.5.dist-info/licenses/LICENSE
rapids_singlecell-0.13.5.dist-info/RECORD
