Metadata-Version: 2.4
Name: rapids_singlecell
Version: 0.13.5
Summary: running single cell analysis on Nvidia GPUs
Project-URL: Documentation, https://rapids-singlecell.readthedocs.io
Project-URL: Source, https://github.com/scverse/rapids_singlecell
Author: Severin Dicks
License: MIT License
License-File: LICENSE
Requires-Python: <3.14,>=3.12
Requires-Dist: anndata>=0.10.0
Requires-Dist: docrep
Requires-Dist: matplotlib>=3.4
Requires-Dist: natsort
Requires-Dist: numpy>=1.17.0
Requires-Dist: pandas
Requires-Dist: scanpy>=1.10.0
Requires-Dist: scikit-image
Requires-Dist: scikit-learn<1.8.0
Requires-Dist: scikit-misc>=0.1.3
Requires-Dist: scipy>=1.4
Requires-Dist: statsmodels>=0.12.0
Requires-Dist: tqdm
Provides-Extra: dev
Requires-Dist: hatch-vcs; extra == 'dev'
Requires-Dist: pre-commit; extra == 'dev'
Provides-Extra: doc
Requires-Dist: dask; extra == 'doc'
Requires-Dist: myst-nb; extra == 'doc'
Requires-Dist: nbsphinx>=0.8.12; extra == 'doc'
Requires-Dist: pytest; extra == 'doc'
Requires-Dist: readthedocs-sphinx-ext; extra == 'doc'
Requires-Dist: scanpydoc[theme,typehints]>=0.9.4; extra == 'doc'
Requires-Dist: sphinx-copybutton; extra == 'doc'
Requires-Dist: sphinx-design; extra == 'doc'
Requires-Dist: sphinx>=4.5.0; extra == 'doc'
Provides-Extra: rapids12
Requires-Dist: cudf-cu12>=25.10; extra == 'rapids12'
Requires-Dist: cugraph-cu12>=25.10; extra == 'rapids12'
Requires-Dist: cuml-cu12>=25.10; extra == 'rapids12'
Requires-Dist: cupy-cuda12x; extra == 'rapids12'
Requires-Dist: cuvs-cu12>=25.10; extra == 'rapids12'
Provides-Extra: rapids13
Requires-Dist: cudf-cu13>=25.10; extra == 'rapids13'
Requires-Dist: cugraph-cu13>=25.10; extra == 'rapids13'
Requires-Dist: cuml-cu13>=25.10; extra == 'rapids13'
Requires-Dist: cupy-cuda13x; extra == 'rapids13'
Requires-Dist: cuvs-cu13>=25.10; extra == 'rapids13'
Provides-Extra: test
Requires-Dist: anyio; extra == 'test'
Requires-Dist: bbknn; extra == 'test'
Requires-Dist: decoupler; extra == 'test'
Requires-Dist: fast-array-utils; extra == 'test'
Requires-Dist: igraph; extra == 'test'
Requires-Dist: pooch; extra == 'test'
Requires-Dist: profimp; extra == 'test'
Requires-Dist: pytest; extra == 'test'
Requires-Dist: scanpy>=1.10.0; extra == 'test'
Provides-Extra: test-minimal
Requires-Dist: anyio; extra == 'test-minimal'
Requires-Dist: bbknn; extra == 'test-minimal'
Requires-Dist: decoupler; extra == 'test-minimal'
Requires-Dist: fast-array-utils; extra == 'test-minimal'
Requires-Dist: pooch; extra == 'test-minimal'
Requires-Dist: profimp; extra == 'test-minimal'
Requires-Dist: pytest; extra == 'test-minimal'
Requires-Dist: scanpy>=1.10.0; extra == 'test-minimal'
